iterjson/__init__.py
iterjson/common.py
iterjson/reader.py
iterjson/values.py
iterjson-1.0.0b1.dist-info/METADATA
iterjson-1.0.0b1.dist-info/WHEEL
iterjson-1.0.0b1.dist-info/top_level.txt
iterjson-1.0.0b1.dist-info/RECORD
